coupons/__init__.py
coupons/admin.py
coupons/apps.py
coupons/exceptions.py
coupons/forms.py
coupons/models.py
coupons/settings.py
coupons/urls.py
coupons/version.py
coupons/views.py
coupons/locale/de/LC_MESSAGES/django.mo
coupons/locale/de/LC_MESSAGES/django.po
coupons/locale/en/LC_MESSAGES/django.mo
coupons/locale/en/LC_MESSAGES/django.po
coupons/locale/it/LC_MESSAGES/django.mo
coupons/locale/it/LC_MESSAGES/django.po
coupons/migrations/0001_initial.py
coupons/migrations/0002_added_timestamp.py
coupons/migrations/0003_added_action.py
coupons/migrations/__init__.py
coupons/tests/__init__.py
coupons/tests/settings.py
coupons/tests/test_admin.py
coupons/tests/test_forms.py
coupons/tests/test_models.py
coupons/tests/test_use_cases.py
django_fluo_coupons-1.2a12.dist-info/DESCRIPTION.rst
django_fluo_coupons-1.2a12.dist-info/METADATA
django_fluo_coupons-1.2a12.dist-info/RECORD
django_fluo_coupons-1.2a12.dist-info/WHEEL
django_fluo_coupons-1.2a12.dist-info/metadata.json
django_fluo_coupons-1.2a12.dist-info/top_level.txt
