Metadata-Version: 2.0
Name: django-fluo-coupons
Version: 1.2a12
Summary: A reuseable Django application for coupon gereration and handling.
Home-page: https://bitbucket.org/rsalmaso/django-fluo-coupons
Author: Raffaele Salmaso
Author-email: raffaele@salmaso.org
License: BSD
Platform: UNKNOWN
Classifier: Framework :: Django
Classifier: Intended Audience :: Developers
Classifier: Programming Language :: Python
Classifier: Programming Language :: Python :: 3
Classifier: Programming Language :: Python :: 3.4
Classifier: Programming Language :: Python :: 3.5
Classifier: Programming Language :: Python :: 3.6
